micropython_hints/__init__.py
micropython_hints/_thread.py
micropython_hints/array.py
micropython_hints/binascii.py
micropython_hints/bluetooth.py
micropython_hints/btree.py
micropython_hints/cmath.py
micropython_hints/collections.py
micropython_hints/cryptolib.py
micropython_hints/errno.py
micropython_hints/esp.py
micropython_hints/esp32.py
micropython_hints/framebuf.py
micropython_hints/gc.py
micropython_hints/hashlib.py
micropython_hints/heapq.py
micropython_hints/io.py
micropython_hints/json.py
micropython_hints/lcd160cr.py
micropython_hints/machine.ADCWiPy.py
micropython_hints/machine.TimerWiPy.py
micropython_hints/machine.py
micropython_hints/math.py
micropython_hints/micropython.py
micropython_hints/neopixel.py
micropython_hints/network.py
micropython_hints/os.py
micropython_hints/pyb.py
micropython_hints/random.py
micropython_hints/re.py
micropython_hints/select.py
micropython_hints/socket.py
micropython_hints/ssl.py
micropython_hints/stm.py
micropython_hints/struct.py
micropython_hints/sys.py
micropython_hints/time.py
micropython_hints/uarray.py
micropython_hints/uasyncio.py
micropython_hints/ubinascii.py
micropython_hints/ubluetooth.py
micropython_hints/ucollections.py
micropython_hints/ucryptolib.py
micropython_hints/uctypes.py
micropython_hints/uerrno.py
micropython_hints/uhashlib.py
micropython_hints/uheapq.py
micropython_hints/uio.py
micropython_hints/ujson.py
micropython_hints/uos.py
micropython_hints/ure.py
micropython_hints/uselect.py
micropython_hints/usocket.py
micropython_hints/ussl.py
micropython_hints/ustruct.py
micropython_hints/usys.py
micropython_hints/utime.py
micropython_hints/uzlib.py
micropython_hints/wipy.py
micropython_hints/zlib.py
micropython_hints-0.0.7.dist-info/METADATA
micropython_hints-0.0.7.dist-info/WHEEL
micropython_hints-0.0.7.dist-info/entry_points.txt
micropython_hints-0.0.7.dist-info/top_level.txt
micropython_hints-0.0.7.dist-info/RECORD
