Metadata-Version: 2.1
Name: micropython-hints
Version: 0.0.7
Summary: MicroPython type hints
Home-page: https://github.com/ITA-ZUFE/micropython_hints
Author: miaobuao
Author-email: miaobuao@outlook.com
License: MIT License
Classifier: Programming Language :: Python :: 3
Classifier: License :: OSI Approved :: Apache Software License
Classifier: Operating System :: OS Independent
Requires-Dist: tqdm
Requires-Dist: meo (>=0.1.13)
